{
    "by_pattern": {
        "A_same_source_line_repeat": {
            "file_count": 3,
            "extra_reports": 12
        },
        "B_multi_source_single_method": {
            "file_count": 70,
            "extra_reports": 84
        },
        "C_cross_method_chain_contains_gt": {
            "file_count": 321,
            "extra_reports": 967
        },
        "D_cross_method_gt_missing": {
            "file_count": 102,
            "extra_reports": 242
        }
    },
    "total_extra_reports": 1305
}